patternpy/__init__.py
patternpy/hard_data.py
patternpy/tradingpatterns.py
m_patternpy-2.0.1.dist-info/LICENSE.md
m_patternpy-2.0.1.dist-info/METADATA
m_patternpy-2.0.1.dist-info/WHEEL
m_patternpy-2.0.1.dist-info/RECORD
