Metadata-Version: 2.3
Name: m-patternpy
Version: 2.0.1
Summary: Trading analysis with high-speed pattern recognition, leveraging Pandas & Numpy. Effortlessly spot Head & Shoulders, Tops & Bottoms, Supports & Resistances. For experts & beginners. #TradingMadeEasy 🔥
Keywords: patternpy
Author: 500apps
Author-email: satyabrata.swain@500apps.com
Requires-Python: >=3.10,<3.13
Classifier: Operating System :: OS Independent
Classifier: Programming Language :: Python :: 3
Classifier: Programming Language :: Python :: 3.10
Classifier: Programming Language :: Python :: 3.11
Classifier: Programming Language :: Python :: 3.12
Classifier: Topic :: Software Development :: Documentation
Classifier: Topic :: Software Development :: Libraries :: Python Modules
Classifier: Topic :: Software Development :: Quality Assurance
Requires-Dist: numpy (>=2.2.4,<3.0.0)
Project-URL: Homepage, https://500apps.com
Project-URL: Repository, https://500apps.com
